{
  "incident": {
    "components": [
      {
        "created_at": "2017-01-31T20:05:05.370Z",
        "description": "Performance of git clones, pulls, pushes, and associated operations",
        "group_id": null,
        "id": "8l4ygp009s5s",
        "name": "Git Operations",
        "page_id": "kctbh9vrtdwd",
        "position": 1,
        "showcase": false,
        "start_date": null,
        "status": "operational",
        "updated_at": "2025-05-26T09:46:21.918Z"
      },
      {
        "created_at": "2017-01-31T20:01:46.621Z",
        "description": "Requests for GitHub APIs",
        "group_id": null,
        "id": "brv1bkgrwx7q",
        "name": "API Requests",
        "page_id": "kctbh9vrtdwd",
        "position": 4,
        "showcase": false,
        "start_date": null,
        "status": "operational",
        "updated_at": "2025-05-26T09:44:00.373Z"
      },
      {
        "created_at": "2017-01-31T20:01:46.638Z",
        "description": "Requests for Issues on GitHub.com",
        "group_id": null,
        "id": "kr09ddfgbfsf",
        "name": "Issues",
        "page_id": "kctbh9vrtdwd",
        "position": 5,
        "showcase": false,
        "start_date": null,
        "status": "partial_outage",
        "updated_at": "2025-05-26T07:35:39.874Z"
      },
      {
        "created_at": "2019-11-13T18:02:19.432Z",
        "description": "Workflows, Compute and Orchestration for GitHub Actions",
        "group_id": null,
        "id": "br0l2tvcx85d",
        "name": "Actions",
        "page_id": "kctbh9vrtdwd",
        "position": 7,
        "showcase": false,
        "start_date": null,
        "status": "operational",
        "updated_at": "2025-05-26T09:42:10.523Z"
      },
      {
        "created_at": "2019-11-13T18:02:40.064Z",
        "description": "API requests and webhook delivery for GitHub Packages",
        "group_id": null,
        "id": "st3j38cctv9l",
        "name": "Packages",
        "page_id": "kctbh9vrtdwd",
        "position": 8,
        "showcase": false,
        "start_date": null,
        "status": "operational",
        "updated_at": "2025-05-26T09:43:17.978Z"
      },
      {
        "created_at": "2022-06-21T16:04:33.017Z",
        "description": null,
        "group_id": null,
        "id": "pjmpxvq2cmr2",
        "name": "Copilot",
        "page_id": "kctbh9vrtdwd",
        "position": 11,
        "showcase": false,
        "start_date": "2022-06-21T00:00:00.000Z",
        "status": "operational",
        "updated_at": "2025-05-26T09:43:19.108Z"
      }
    ],
    "created_at": "2025-05-26T07:21:51.216Z",
    "id": "d0nm3xcdc5jw",
    "impact": "minor",
    "impact_override": "minor",
    "incident_updates": [
      {
        "affected_components": [
          {
            "code": "brv1bkgrwx7q",
            "name": "API Requests",
            "new_status": "operational",
            "old_status": "operational"
          },
          {
            "code": "kr09ddfgbfsf",
            "name": "Issues",
            "new_status": "partial_outage",
            "old_status": "partial_outage"
          },
          {
            "code": "8l4ygp009s5s",
            "name": "Git Operations",
            "new_status": "operational",
            "old_status": "partial_outage"
          },
          {
            "code": "br0l2tvcx85d",
            "name": "Actions",
            "new_status": "operational",
            "old_status": "operational"
          },
          {
            "code": "st3j38cctv9l",
            "name": "Packages",
            "new_status": "operational",
            "old_status": "operational"
          },
          {
            "code": "pjmpxvq2cmr2",
            "name": "Copilot",
            "new_status": "operational",
            "old_status": "operational"
          }
        ],
        "body": "Git Operations is operating normally.",
        "created_at": "2025-05-26T09:46:21.951Z",
        "custom_tweet": null,
        "deliver_notifications": true,
        "display_at": "2025-05-26T09:46:21.951Z",
        "id": "zfntkfty7801",
        "incident_id": "d0nm3xcdc5jw",
        "status": "investigating",
        "tweet_id": null,
        "twitter_updated_at": null,
        "updated_at": "2025-05-26T09:46:21.951Z",
        "wants_twitter_update": false
      },
      {
        "affected_components": [
          {
            "code": "brv1bkgrwx7q",
            "name": "API Requests",
            "new_status": "operational",
            "old_status": "partial_outage"
          },
          {
            "code": "kr09ddfgbfsf",
            "name": "Issues",
            "new_status": "partial_outage",
            "old_status": "partial_outage"
          },
          {
            "code": "8l4ygp009s5s",
            "name": "Git Operations",
            "new_status": "partial_outage",
            "old_status": "partial_outage"
          },
          {
            "code": "br0l2tvcx85d",
            "name": "Actions",
            "new_status": "operational",
            "old_status": "operational"
          },
          {
            "code": "st3j38cctv9l",
            "name": "Packages",
            "new_status": "operational",
            "old_status": "operational"
          },
          {
            "code": "pjmpxvq2cmr2",
            "name": "Copilot",
            "new_status": "operational",
            "old_status": "operational"
          }
        ],
        "body": "API Requests is operating normally.",
        "created_at": "2025-05-26T09:44:00.411Z",
        "custom_tweet": null,
        "deliver_notifications": true,
        "display_at": "2025-05-26T09:44:00.411Z",
        "id": "zsmgqzcn8r4w",
        "incident_id": "d0nm3xcdc5jw",
        "status": "investigating",
        "tweet_id": null,
        "twitter_updated_at": null,
        "updated_at": "2025-05-26T09:44:00.411Z",
        "wants_twitter_update": false
      },
      {
        "affected_components": [
          {
            "code": "brv1bkgrwx7q",
            "name": "API Requests",
            "new_status": "partial_outage",
            "old_status": "partial_outage"
          },
          {
            "code": "kr09ddfgbfsf",
            "name": "Issues",
            "new_status": "partial_outage",
            "old_status": "partial_outage"
          },
          {
            "code": "8l4ygp009s5s",
            "name": "Git Operations",
            "new_status": "partial_outage",
            "old_status": "partial_outage"
          },
          {
            "code": "br0l2tvcx85d",
            "name": "Actions",
            "new_status": "operational",
            "old_status": "operational"
          },
          {
            "code": "st3j38cctv9l",
            "name": "Packages",
            "new_status": "operational",
            "old_status": "operational"
          },
          {
            "code": "pjmpxvq2cmr2",
            "name": "Copilot",
            "new_status": "operational",
            "old_status": "partial_outage"
          }
        ],
        "body": "Copilot is operating normally.",
        "created_at": "2025-05-26T09:43:19.138Z",
        "custom_tweet": null,
        "deliver_notifications": true,
        "display_at": "2025-05-26T09:43:19.138Z",
        "id": "lk40q2h8qr5t",
        "incident_id": "d0nm3xcdc5jw",
        "status": "investigating",
        "tweet_id": null,
        "twitter_updated_at": null,
        "updated_at": "2025-05-26T09:43:19.138Z",
        "wants_twitter_update": false
      },
      {
        "affected_components": [
          {
            "code": "brv1bkgrwx7q",
            "name": "API Requests",
            "new_status": "partial_outage",
            "old_status": "partial_outage"
          },
          {
            "code": "kr09ddfgbfsf",
            "name": "Issues",
            "new_status": "partial_outage",
            "old_status": "partial_outage"
          },
          {
            "code": "8l4ygp009s5s",
            "name": "Git Operations",
            "new_status": "partial_outage",
            "old_status": "partial_outage"
          },
          {
            "code": "br0l2tvcx85d",
            "name": "Actions",
            "new_status": "operational",
            "old_status": "operational"
          },
          {
            "code": "st3j38cctv9l",
            "name": "Packages",
            "new_status": "operational",
            "old_status": "partial_outage"
          },
          {
            "code": "pjmpxvq2cmr2",
            "name": "Copilot",
            "new_status": "partial_outage",
            "old_status": "partial_outage"
          }
        ],
        "body": "Packages is operating normally.",
        "created_at": "2025-05-26T09:43:18.006Z",
        "custom_tweet": null,
        "deliver_notifications": true,
        "display_at": "2025-05-26T09:43:18.006Z",
        "id": "vh9qjss69f9v",
        "incident_id": "d0nm3xcdc5jw",
        "status": "investigating",
        "tweet_id": null,
        "twitter_updated_at": null,
        "updated_at": "2025-05-26T09:43:18.006Z",
        "wants_twitter_update": false
      },
      {
        "affected_components": [
          {
            "code": "brv1bkgrwx7q",
            "name": "API Requests",
            "new_status": "partial_outage",
            "old_status": "partial_outage"
          },
          {
            "code": "kr09ddfgbfsf",
            "name": "Issues",
            "new_status": "partial_outage",
            "old_status": "partial_outage"
          },
          {
            "code": "8l4ygp009s5s",
            "name": "Git Operations",
            "new_status": "partial_outage",
            "old_status": "partial_outage"
          },
          {
            "code": "br0l2tvcx85d",
            "name": "Actions",
            "new_status": "operational",
            "old_status": "partial_outage"
          },
          {
            "code": "st3j38cctv9l",
            "name": "Packages",
            "new_status": "partial_outage",
            "old_status": "partial_outage"
          },
          {
            "code": "pjmpxvq2cmr2",
            "name": "Copilot",
            "new_status": "partial_outage",
            "old_status": "partial_outage"
          }
        ],
        "body": "Actions is operating normally.",
        "created_at": "2025-05-26T09:42:10.555Z",
        "custom_tweet": null,
        "deliver_notifications": true,
        "display_at": "2025-05-26T09:42:10.555Z",
        "id": "3t42xr30j26b",
        "incident_id": "d0nm3xcdc5jw",
        "status": "investigating",
        "tweet_id": null,
        "twitter_updated_at": null,
        "updated_at": "2025-05-26T09:42:10.555Z",
        "wants_twitter_update": false
      },
      {
        "affected_components": [
          {
            "code": "brv1bkgrwx7q",
            "name": "API Requests",
            "new_status": "partial_outage",
            "old_status": "partial_outage"
          },
          {
            "code": "kr09ddfgbfsf",
            "name": "Issues",
            "new_status": "partial_outage",
            "old_status": "partial_outage"
          },
          {
            "code": "8l4ygp009s5s",
            "name": "Git Operations",
            "new_status": "partial_outage",
            "old_status": "partial_outage"
          },
          {
            "code": "br0l2tvcx85d",
            "name": "Actions",
            "new_status": "partial_outage",
            "old_status": "partial_outage"
          },
          {
            "code": "st3j38cctv9l",
            "name": "Packages",
            "new_status": "partial_outage",
            "old_status": "operational"
          },
          {
            "code": "pjmpxvq2cmr2",
            "name": "Copilot",
            "new_status": "partial_outage",
            "old_status": "partial_outage"
          }
        ],
        "body": "Packages is experiencing degraded performance. We are continuing to investigate.",
        "created_at": "2025-05-26T08:39:25.479Z",
        "custom_tweet": null,
        "deliver_notifications": true,
        "display_at": "2025-05-26T08:39:25.479Z",
        "id": "566bjn0gxvnx",
        "incident_id": "d0nm3xcdc5jw",
        "status": "investigating",
        "tweet_id": null,
        "twitter_updated_at": null,
        "updated_at": "2025-05-26T08:39:25.479Z",
        "wants_twitter_update": false
      },
      {
        "affected_components": [
          {
            "code": "brv1bkgrwx7q",
            "name": "API Requests",
            "new_status": "partial_outage",
            "old_status": "partial_outage"
          },
          {
            "code": "kr09ddfgbfsf",
            "name": "Issues",
            "new_status": "partial_outage",
            "old_status": "partial_outage"
          },
          {
            "code": "8l4ygp009s5s",
            "name": "Git Operations",
            "new_status": "partial_outage",
            "old_status": "partial_outage"
          },
          {
            "code": "br0l2tvcx85d",
            "name": "Actions",
            "new_status": "partial_outage",
            "old_status": "partial_outage"
          },
          {
            "code": "pjmpxvq2cmr2",
            "name": "Copilot",
            "new_status": "partial_outage",
            "old_status": "operational"
          }
        ],
        "body": "Copilot is experiencing degraded performance. We are continuing to investigate.",
        "created_at": "2025-05-26T08:26:06.270Z",
        "custom_tweet": null,
        "deliver_notifications": true,
        "display_at": "2025-05-26T08:26:06.270Z",
        "id": "zd2h4h067j2s",
        "incident_id": "d0nm3xcdc5jw",
        "status": "investigating",
        "tweet_id": null,
        "twitter_updated_at": null,
        "updated_at": "2025-05-26T08:26:06.270Z",
        "wants_twitter_update": false
      },
      {
        "affected_components": [
          {
            "code": "brv1bkgrwx7q",
            "name": "API Requests",
            "new_status": "partial_outage",
            "old_status": "partial_outage"
          },
          {
            "code": "kr09ddfgbfsf",
            "name": "Issues",
            "new_status": "partial_outage",
            "old_status": "partial_outage"
          },
          {
            "code": "8l4ygp009s5s",
            "name": "Git Operations",
            "new_status": "partial_outage",
            "old_status": "partial_outage"
          },
          {
            "code": "br0l2tvcx85d",
            "name": "Actions",
            "new_status": "partial_outage",
            "old_status": "operational"
          }
        ],
        "body": "Actions is experiencing degraded performance. We are continuing to investigate.",
        "created_at": "2025-05-26T08:25:10.157Z",
        "custom_tweet": null,
        "deliver_notifications": true,
        "display_at": "2025-05-26T08:25:10.157Z",
        "id": "tf4zwlwsnnln",
        "incident_id": "d0nm3xcdc5jw",
        "status": "investigating",
        "tweet_id": null,
        "twitter_updated_at": null,
        "updated_at": "2025-05-26T08:25:10.157Z",
        "wants_twitter_update": false
      },
      {
        "affected_components": [
          {
            "code": "brv1bkgrwx7q",
            "name": "API Requests",
            "new_status": "partial_outage",
            "old_status": "partial_outage"
          },
          {
            "code": "kr09ddfgbfsf",
            "name": "Issues",
            "new_status": "partial_outage",
            "old_status": "partial_outage"
          },
          {
            "code": "8l4ygp009s5s",
            "name": "Git Operations",
            "new_status": "partial_outage",
            "old_status": "partial_outage"
          }
        ],
        "body": "We are continuing to investigate degraded performance.",
        "created_at": "2025-05-26T07:53:32.528Z",
        "custom_tweet": null,
        "deliver_notifications": true,
        "display_at": "2025-05-26T07:53:32.528Z",
        "id": "kz0qmgxx9x5m",
        "incident_id": "d0nm3xcdc5jw",
        "status": "investigating",
        "tweet_id": null,
        "twitter_updated_at": null,
        "updated_at": "2025-05-26T07:53:32.528Z",
        "wants_twitter_update": false
      },
      {
        "affected_components": [
          {
            "code": "brv1bkgrwx7q",
            "name": "API Requests",
            "new_status": "partial_outage",
            "old_status": "partial_outage"
          },
          {
            "code": "kr09ddfgbfsf",
            "name": "Issues",
            "new_status": "partial_outage",
            "old_status": "operational"
          },
          {
            "code": "8l4ygp009s5s",
            "name": "Git Operations",
            "new_status": "partial_outage",
            "old_status": "partial_outage"
          }
        ],
        "body": "Issues is experiencing degraded performance. We are continuing to investigate.",
        "created_at": "2025-05-26T07:35:39.919Z",
        "custom_tweet": null,
        "deliver_notifications": true,
        "display_at": "2025-05-26T07:35:39.919Z",
        "id": "b2qtmcc0tt15",
        "incident_id": "d0nm3xcdc5jw",
        "status": "investigating",
        "tweet_id": null,
        "twitter_updated_at": null,
        "updated_at": "2025-05-26T07:35:39.919Z",
        "wants_twitter_update": false
      },
      {
        "affected_components": [
          {
            "code": "brv1bkgrwx7q",
            "name": "API Requests",
            "new_status": "partial_outage",
            "old_status": "operational"
          },
          {
            "code": "8l4ygp009s5s",
            "name": "Git Operations",
            "new_status": "partial_outage",
            "old_status": "operational"
          }
        ],
        "body": "We are investigating reports of degraded performance for API Requests and Git Operations",
        "created_at": "2025-05-26T07:21:51.381Z",
        "custom_tweet": null,
        "deliver_notifications": true,
        "display_at": "2025-05-26T07:21:51.381Z",
        "id": "xbwkysx6xs16",
        "incident_id": "d0nm3xcdc5jw",
        "status": "investigating",
        "tweet_id": null,
        "twitter_updated_at": null,
        "updated_at": "2025-05-26T07:21:51.381Z",
        "wants_twitter_update": false
      }
    ],
    "metadata": {},
    "monitoring_at": null,
    "name": "We're experiencing errors",
    "page_id": "kctbh9vrtdwd",
    "postmortem_body": null,
    "postmortem_body_last_updated_at": null,
    "postmortem_ignored": false,
    "postmortem_notified_subscribers": false,
    "postmortem_notified_twitter": false,
    "postmortem_published_at": null,
    "reminder_intervals": null,
    "resolved_at": null,
    "scheduled_auto_completed": false,
    "scheduled_auto_in_progress": false,
    "scheduled_for": null,
    "scheduled_remind_prior": false,
    "scheduled_reminded_at": null,
    "scheduled_until": null,
    "shortlink": "https://stspg.io/76rvy4nf5wm2",
    "started_at": "2025-05-26T07:21:51.205Z",
    "status": "investigating",
    "updated_at": "2025-05-26T09:46:21.954Z"
  },
  "meta": {
    "generated_at": "2025-05-26T09:47:43.308Z"
  },
  "page": {
    "id": "kctbh9vrtdwd",
    "status_description": "Minor Service Outage",
    "status_indicator": "minor"
  }
}
