{
  "component": {
    "created_at": "2019-11-13T18:02:19.432Z",
    "description": "Workflows, Compute and Orchestration for GitHub Actions",
    "group_id": null,
    "id": "br0l2tvcx85d",
    "name": "Actions",
    "page_id": "kctbh9vrtdwd",
    "position": 7,
    "showcase": true,
    "start_date": null,
    "status": "operational",
    "updated_at": "2026-05-15T08:26:58.567Z"
  },
  "component_update": {
    "component_id": "br0l2tvcx85d",
    "component_type": "Component",
    "created_at": "2026-05-15T08:26:58.574Z",
    "id": "m1lkhvjd4psh",
    "new_status": "operational",
    "old_status": "partial_outage",
    "state": "sn_created"
  },
  "meta": {
    "generated_at": "2026-05-15T08:27:10.377Z"
  },
  "page": {
    "id": "kctbh9vrtdwd",
    "status_description": "Partial System Outage",
    "status_indicator": "major"
  }
}
